<indicator id="tZhYsw0sliDInwowT0iWTLQ" min="0.0" max="5.95697451594" first_time="2008.0" last_time="2008.0" scale="lin" closestBelowZero="0" closestAboveZero="0.012573871495" dataCollectionUrl="N/A" providerSourceName="N/A">
  <data>
    <t1 m="i1,5.95697451594162963317558,5.95697451594162963317558,2008" d="5.95697451594162963317558"/>
    <t1 m="i3,0.151926207270750013300642,0.151926207270750013300642,2008" d="0.151926207270750013300642"/>
    <t1 m="i4,0.443691739215629987747036,0.443691739215629987747036,2008" d="0.443691739215629987747036"/>
    <t1 m="i7,3.47045396381421999976169,3.47045396381421999976169,2008" d="3.47045396381421999976169"/>
    <t1 m="i10,0.120420397764529993334115,0.120420397764529993334115,2008" d="0.120420397764529993334115"/>
    <t1 m="i11,1.379866683649640046738227,1.379866683649640046738227,2008" d="1.379866683649640046738227"/>
    <t1 m="i13,0.04489707345909500074698784,0.04489707345909500074698784,2008" d="0.04489707345909500074698784"/>
    <t1 m="i14,0.09227524387028700203483567,0.09227524387028700203483567,2008" d="0.09227524387028700203483567"/>
    <t1 m="i15,1.037957878220989949014097,1.037957878220989949014097,2008" d="1.037957878220989949014097"/>
    <t1 m="i16,0.1771165426850900004307476,0.1771165426850900004307476,2008" d="0.1771165426850900004307476"/>
    <t1 m="i17,0,0,2008" d="0"/>
    <t1 m="i18,1.140677425929589983155665,1.140677425929589983155665,2008" d="1.140677425929589983155665"/>
    <t1 m="i19,0,0,2008" d="0"/>
    <t1 m="i20,0.2595919214994000245866346,0.2595919214994000245866346,2008" d="0.2595919214994000245866346"/>
    <t1 m="i21,0.168140700137879989251033,0.168140700137879989251033,2008" d="0.168140700137879989251033"/>
    <t1 m="i22,0.1344989912575700052865812,0.1344989912575700052865812,2008" d="0.1344989912575700052865812"/>
    <t1 m="i23,2.946563902690240155379797,2.946563902690240155379797,2008" d="2.946563902690240155379797"/>
    <t1 m="i25,2.983860029838599992046966,2.983860029838599992046966,2008" d="2.983860029838599992046966"/>
    <t1 m="i26,1.366130615786230073638308,1.366130615786230073638308,2008" d="1.366130615786230073638308"/>
    <t1 m="i27,0.08730574471800199576332346,0.08730574471800199576332346,2008" d="0.08730574471800199576332346"/>
    <t1 m="i28,2.943854967490520113670982,2.943854967490520113670982,2008" d="2.943854967490520113670982"/>
    <t1 m="i29,0.2988860696546299933196167,0.2988860696546299933196167,2008" d="0.2988860696546299933196167"/>
    <t1 m="i31,0.1286173633440499952662606,0.1286173633440499952662606,2008" d="0.1286173633440499952662606"/>
    <t1 m="i32,0.178839196049030008106584,0.178839196049030008106584,2008" d="0.178839196049030008106584"/>
    <t1 m="i33,1.952030277973550109749112,1.952030277973550109749112,2008" d="1.952030277973550109749112"/>
    <t1 m="i34,3.693480736245839946008118,3.693480736245839946008118,2008" d="3.693480736245839946008118"/>
    <t1 m="i35,3.191253805701629975288824,3.191253805701629975288824,2008" d="3.191253805701629975288824"/>
    <t1 m="i36,3.414801068314480048115911,3.414801068314480048115911,2008" d="3.414801068314480048115911"/>
    <t1 m="i37,0.0424802820690729984742795,0.0424802820690729984742795,2008" d="0.0424802820690729984742795"/>
    <t1 m="i38,1.080093054170820021653299,1.080093054170820021653299,2008" d="1.080093054170820021653299"/>
    <t1 m="i40,3.130825641591910013517008,3.130825641591910013517008,2008" d="3.130825641591910013517008"/>
    <t1 m="i41,3.073657431650239857390261,3.073657431650239857390261,2008" d="3.073657431650239857390261"/>
    <t1 m="i43,0.09951476600097899916086419,0.09951476600097899916086419,2008" d="0.09951476600097899916086419"/>
    <t1 m="i44,0.4104504670438799962539633,0.4104504670438799962539633,2008" d="0.4104504670438799962539633"/>
    <t1 m="i47,0.2874348508224000009469989,0.2874348508224000009469989,2008" d="0.2874348508224000009469989"/>
    <t1 m="i48,4.149571055576280365073671,4.149571055576280365073671,2008" d="4.149571055576280365073671"/>
    <t1 m="i50,2.447138607210260108359989,2.447138607210260108359989,2008" d="2.447138607210260108359989"/>
    <t1 m="i52,0.06628135107905999690025567,0.06628135107905999690025567,2008" d="0.06628135107905999690025567"/>
    <t1 m="i53,2.662529264271960016685625,2.662529264271960016685625,2008" d="2.662529264271960016685625"/>
    <t1 m="i54,0.02371354043158600127805258,0.02371354043158600127805258,2008" d="0.02371354043158600127805258"/>
    <t1 m="i55,0.08510058889607499676976943,0.08510058889607499676976943,2008" d="0.08510058889607499676976943"/>
    <t1 m="i56,0,0,2008" d="0"/>
    <t1 m="i57,0.07333260000733299310837765,0.07333260000733299310837765,2008" d="0.07333260000733299310837765"/>
    <t1 m="i116,1.937771257411819991745006,1.937771257411819991745006,2008" d="1.937771257411819991745006"/>
    <t1 m="i49,3.676978862222440191942496,3.676978862222440191942496,2008" d="3.676978862222440191942496"/>
    <t1 m="i59,0.0160438960997290012977512,0.0160438960997290012977512,2008" d="0.0160438960997290012977512"/>
    <t1 m="i60,1.447357538665120069154568,1.447357538665120069154568,2008" d="1.447357538665120069154568"/>
    <t1 m="i62,0.3434770584089399947380628,0.3434770584089399947380628,2008" d="0.3434770584089399947380628"/>
    <t1 m="i64,0.548356887754190003292365,0.548356887754190003292365,2008" d="0.548356887754190003292365"/>
    <t1 m="i65,0.9146016173015000250146045,0.9146016173015000250146045,2008" d="0.9146016173015000250146045"/>
    <t1 m="i66,0.80427229442799996750324,0.80427229442799996750324,2008" d="0.80427229442799996750324"/>
    <t1 m="i67,2.433769549952120136993017,2.433769549952120136993017,2008" d="2.433769549952120136993017"/>
    <t1 m="i68,1.04370371997978006461949,1.04370371997978006461949,2008" d="1.04370371997978006461949"/>
    <t1 m="i70,0.06275888038157399761995947,0.06275888038157399761995947,2008" d="0.06275888038157399761995947"/>
    <t1 m="i71,2.197478896508020085320823,2.197478896508020085320823,2008" d="2.197478896508020085320823"/>
    <t1 m="i74,0.1131413701419899942024472,0.1131413701419899942024472,2008" d="0.1131413701419899942024472"/>
    <t1 m="i75,0.03389256058295200130237035,0.03389256058295200130237035,2008" d="0.03389256058295200130237035"/>
    <t1 m="i76,0.04655877446663599789067334,0.04655877446663599789067334,2008" d="0.04655877446663599789067334"/>
    <t1 m="i79,1.845998229864709960779123,1.845998229864709960779123,2008" d="1.845998229864709960779123"/>
    <t1 m="i80,1.096634804242500038640173,1.096634804242500038640173,2008" d="1.096634804242500038640173"/>
    <t1 m="i81,0.4983325027791600247972781,0.4983325027791600247972781,2008" d="0.4983325027791600247972781"/>
    <t1 m="i82,0.0705809563569410047811914,0.0705809563569410047811914,2008" d="0.0705809563569410047811914"/>
    <t1 m="i83,0.7851794082073699776458398,0.7851794082073699776458398,2008" d="0.7851794082073699776458398"/>
    <t1 m="i85,0.01874589933452100107280636,0.01874589933452100107280636,2008" d="0.01874589933452100107280636"/>
    <t1 m="i87,0,0,2008" d="0"/>
    <t1 m="i90,1.108995232645989981179468,1.108995232645989981179468,2008" d="1.108995232645989981179468"/>
    <t1 m="i92,2.590706605026889874920926,2.590706605026889874920926,2008" d="2.590706605026889874920926"/>
    <t1 m="i93,5.462967237585210078520959,5.462967237585210078520959,2008" d="5.462967237585210078520959"/>
    <t1 m="i94,0.807517251504920041682567,0.807517251504920041682567,2008" d="0.807517251504920041682567"/>
    <t1 m="i95,1.793662879231580076222485,1.793662879231580076222485,2008" d="1.793662879231580076222485"/>
    <t1 m="i97,0.6996025662017499868738923,0.6996025662017499868738923,2008" d="0.6996025662017499868738923"/>
    <t1 m="i99,0.1318485161970799901531848,0.1318485161970799901531848,2008" d="0.1318485161970799901531848"/>
    <t1 m="i100,0.2163097555699800000894584,0.2163097555699800000894584,2008" d="0.2163097555699800000894584"/>
    <t1 m="i101,1.110064853054169908830318,1.110064853054169908830318,2008" d="1.110064853054169908830318"/>
    <t1 m="i102,0.7182944452686199632296393,0.7182944452686199632296393,2008" d="0.7182944452686199632296393"/>
    <t1 m="i103,0.3235648924164700179773035,0.3235648924164700179773035,2008" d="0.3235648924164700179773035"/>
    <t1 m="i104,1.030654831260729986652791,1.030654831260729986652791,2008" d="1.030654831260729986652791"/>
    <t1 m="i105,0.144715705995569987596383,0.144715705995569987596383,2008" d="0.144715705995569987596383"/>
    <t1 m="i107,0.05003860120664500171772104,0.05003860120664500171772104,2008" d="0.05003860120664500171772104"/>
    <t1 m="i108,0.03663674665689699988524453,0.03663674665689699988524453,2008" d="0.03663674665689699988524453"/>
    <t1 m="i109,0.4770992366412200036407398,0.4770992366412200036407398,2008" d="0.4770992366412200036407398"/>
    <t1 m="i110,0.0125738714950329993208511,0.0125738714950329993208511,2008" d="0.0125738714950329993208511"/>
    <t1 m="i112,0.2867831218573300144925042,0.2867831218573300144925042,2008" d="0.2867831218573300144925042"/>
    <t1 m="i113,0.6671793759407900203939334,0.6671793759407900203939334,2008" d="0.6671793759407900203939334"/>
    <t1 m="i114,2.43908592035328997127408,2.43908592035328997127408,2008" d="2.43908592035328997127408"/>
    <t1 m="i119,0,0,2008" d="0"/>
    <t1 m="i120,1.347070122483599918794539,1.347070122483599918794539,2008" d="1.347070122483599918794539"/>
    <t1 m="i121,2.567696493563090154310657,2.567696493563090154310657,2008" d="2.567696493563090154310657"/>
    <t1 m="i122,0.04323576462449699869816655,0.04323576462449699869816655,2008" d="0.04323576462449699869816655"/>
    <t1 m="i123,0.379149794500809989017398,0.379149794500809989017398,2008" d="0.379149794500809989017398"/>
    <t1 m="i124,2.106256424082090017435576,2.106256424082090017435576,2008" d="2.106256424082090017435576"/>
    <t1 m="i125,2.385945611441540048502929,2.385945611441540048502929,2008" d="2.385945611441540048502929"/>
    <t1 m="i126,0.06813752878810599988845809,0.06813752878810599988845809,2008" d="0.06813752878810599988845809"/>
    <t1 m="i128,0.1273236567354200099444483,0.1273236567354200099444483,2008" d="0.1273236567354200099444483"/>
    <t1 m="i129,0,0,2008" d="0"/>
    <t1 m="i132,2.9160373322623698300049,2.9160373322623698300049,2008" d="2.9160373322623698300049"/>
    <t1 m="i133,2.655975945878230159991062,2.655975945878230159991062,2008" d="2.655975945878230159991062"/>
    <t1 m="i134,0.02360919160311900077964253,0.02360919160311900077964253,2008" d="0.02360919160311900077964253"/>
    <t1 m="i135,0.6986899563318800243649775,0.6986899563318800243649775,2008" d="0.6986899563318800243649775"/>
    <t1 m="i136,1.958145109246800075197825,1.958145109246800075197825,2008" d="1.958145109246800075197825"/>
    <t1 m="i137,0.2717391304347799851903744,0.2717391304347799851903744,2008" d="0.2717391304347799851903744"/>
    <t1 m="i140,2.53793001241177007543115,2.53793001241177007543115,2008" d="2.53793001241177007543115"/>
    <t1 m="i141,0.2210921954454999893702194,0.2210921954454999893702194,2008" d="0.2210921954454999893702194"/>
    <t1 m="i143,0.06296860356138700431927191,0.06296860356138700431927191,2008" d="0.06296860356138700431927191"/>
    <t1 m="i144,1.79340028694404995945888,1.79340028694404995945888,2008" d="1.79340028694404995945888"/>
    <t1 m="i147,1.490793343809180049319707,1.490793343809180049319707,2008" d="1.490793343809180049319707"/>
    <t1 m="i148,0,0,2008" d="0"/>
    <t1 m="i150,0.4934635417069500040732066,0.4934635417069500040732066,2008" d="0.4934635417069500040732066"/>
    <t1 m="i151,2.954937769466940089557738,2.954937769466940089557738,2008" d="2.954937769466940089557738"/>
    <t1 m="i152,1.9329176563348899886563,1.9329176563348899886563,2008" d="1.9329176563348899886563"/>
    <t1 m="i153,0.8511942254983699829296029,0.8511942254983699829296029,2008" d="0.8511942254983699829296029"/>
    <t1 m="i155,1.072795678205030078800064,1.072795678205030078800064,2008" d="1.072795678205030078800064"/>
    <t1 m="i156,0.07024217340091000461033133,0.07024217340091000461033133,2008" d="0.07024217340091000461033133"/>
    <t1 m="i159,0.1201489847410800032578848,0.1201489847410800032578848,2008" d="0.1201489847410800032578848"/>
    <t1 m="i161,0.735871972565550036549098,0.735871972565550036549098,2008" d="0.735871972565550036549098"/>
    <t1 m="i162,3.585893209949940096947785,3.585893209949940096947785,2008" d="3.585893209949940096947785"/>
    <t1 m="i163,2.925888280073050129459489,2.925888280073050129459489,2008" d="2.925888280073050129459489"/>
    <t1 m="i168,0.06888356954657399999764067,0.06888356954657399999764067,2008" d="0.06888356954657399999764067"/>
    <t1 m="i169,0.06517948801512199463736863,0.06517948801512199463736863,2008" d="0.06517948801512199463736863"/>
    <t1 m="i170,1.165089074601109997431081,1.165089074601109997431081,2008" d="1.165089074601109997431081"/>
    <t1 m="i172,0.2708752120667800022957294,0.2708752120667800022957294,2008" d="0.2708752120667800022957294"/>
    <t1 m="i173,3.180218845454899856406428,3.180218845454899856406428,2008" d="3.180218845454899856406428"/>
    <t1 m="i174,0.4815012427937500061325693,0.4815012427937500061325693,2008" d="0.4815012427937500061325693"/>
    <t1 m="i175,0.7570395647597299992881403,0.7570395647597299992881403,2008" d="0.7570395647597299992881403"/>
    <t1 m="i176,1.109669420489570068610874,1.109669420489570068610874,2008" d="1.109669420489570068610874"/>
    <t1 m="i178,0.04835667886329599735040219,0.04835667886329599735040219,2008" d="0.04835667886329599735040219"/>
    <t1 m="i179,0.04778607131593300139105196,0.04778607131593300139105196,2008" d="0.04778607131593300139105196"/>
    <t1 m="i181,0,0,2008" d="0"/>
    <t1 m="i117,0.02656836372089900130677442,0.02656836372089900130677442,2008" d="0.02656836372089900130677442"/>
    <t1 m="i145,0.2893325321047799936202694,0.2893325321047799936202694,2008" d="0.2893325321047799936202694"/>
    <t1 m="i183,0.07022307530254399965397027,0.07022307530254399965397027,2008" d="0.07022307530254399965397027"/>
    <t1 m="i184,0.1805405734201599998733911,0.1805405734201599998733911,2008" d="0.1805405734201599998733911"/>
    <t1 m="i185,2.865955181919920047306505,2.865955181919920047306505,2008" d="2.865955181919920047306505"/>
    <t1 m="i189,0,0,2008" d="0"/>
    <t1 m="i191,0,0,2008" d="0"/>
    <t1 m="i193,0.7122507122507100163488758,0.7122507122507100163488758,2008" d="0.7122507122507100163488758"/>
    <t1 m="i195,3.497862417411579993853366,3.497862417411579993853366,2008" d="3.497862417411579993853366"/>
    <t1 m="i196,0.07957698904377200066484477,0.07957698904377200066484477,2008" d="0.07957698904377200066484477"/>
    <t1 m="i197,0.9803838170744200164463678,0.9803838170744200164463678,2008" d="0.9803838170744200164463678"/>
    <t1 m="i198,0.07859095156177700602917469,0.07859095156177700602917469,2008" d="0.07859095156177700602917469"/>
    <t1 m="i202,2.782594668709919893956339,2.782594668709919893956339,2008" d="2.782594668709919893956339"/>
    <t1 m="i203,0.02689256420599700145301902,0.02689256420599700145301902,2008" d="0.02689256420599700145301902"/>
    <t1 m="i204,0.07279212389219499867998309,0.07279212389219499867998309,2008" d="0.07279212389219499867998309"/>
    <t1 m="i205,0,0,2008" d="0"/>
    <t1 m="i206,1.670951156812340077095769,1.670951156812340077095769,2008" d="1.670951156812340077095769"/>
    <t1 m="i207,3.3312844795531999508853,3.3312844795531999508853,2008" d="3.3312844795531999508853"/>
    <t1 m="i209,0.5561934013654700192930136,0.5561934013654700192930136,2008" d="0.5561934013654700192930136"/>
    <t1 m="i212,0.09566904210862700597139963,0.09566904210862700597139963,2008" d="0.09566904210862700597139963"/>
    <t1 m="i213,0.09029197140207000094047629,0.09029197140207000094047629,2008" d="0.09029197140207000094047629"/>
    <t1 m="i214,1.914409461395830014396324,1.914409461395830014396324,2008" d="1.914409461395830014396324"/>
    <t1 m="i215,0.7161857990587300326623676,0.7161857990587300326623676,2008" d="0.7161857990587300326623676"/>
    <t1 m="i217,1.797945205479450025976007,1.797945205479450025976007,2008" d="1.797945205479450025976007"/>
    <t1 m="i218,0.04660136262384299843386515,0.04660136262384299843386515,2008" d="0.04660136262384299843386515"/>
    <t1 m="i219,0.01378055838822600000226348,0.01378055838822600000226348,2008" d="0.01378055838822600000226348"/>
    <t1 m="i220,0.2168693887163500033654628,0.2168693887163500033654628,2008" d="0.2168693887163500033654628"/>
    <t1 m="i222,1.939481940519099945063886,1.939481940519099945063886,2008" d="1.939481940519099945063886"/>
    <t1 m="i224,0.03787789599548700009146174,0.03787789599548700009146174,2008" d="0.03787789599548700009146174"/>
    <t1 m="i131,0,0,2008" d="0"/>
    <t1 m="i226,1.762623912461050101896376,1.762623912461050101896376,2008" d="1.762623912461050101896376"/>
    <t1 m="i228,0,0,2008" d="0"/>
    <t1 m="i230,0,0,2008" d="0"/>
    <t1 m="i231,0.9291407892806500257165681,0.9291407892806500257165681,2008" d="0.9291407892806500257165681"/>
    <t1 m="i232,0.5237035185310200402497571,0.5237035185310200402497571,2008" d="0.5237035185310200402497571"/>
    <t1 m="i233,1.147586904858719947242207,1.147586904858719947242207,2008" d="1.147586904858719947242207"/>
    <t1 m="i236,2.798108394120490061141027,2.798108394120490061141027,2008" d="2.798108394120490061141027"/>
    <t1 m="i237,0.3313445394637899998890873,0.3313445394637899998890873,2008" d="0.3313445394637899998890873"/>
    <t1 m="i238,0.06393248729341799441172611,0.06393248729341799441172611,2008" d="0.06393248729341799441172611"/>
    <t1 m="i239,0.09286763132357900296653952,0.09286763132357900296653952,2008" d="0.09286763132357900296653952"/>
    <t1 m="i223,3.056386204373669812639491,3.056386204373669812639491,2008" d="3.056386204373669812639491"/>
    <t1 m="i240,0.0366000258246140033890903,0.0366000258246140033890903,2008" d="0.0366000258246140033890903"/>
    <t1 m="i241,0.1390102470410700119529679,0.1390102470410700119529679,2008" d="0.1390102470410700119529679"/>
    <t1 m="i243,1.138639271849219980481394,1.138639271849219980481394,2008" d="1.138639271849219980481394"/>
    <t1 m="i245,1.273705066515709916075139,1.273705066515709916075139,2008" d="1.273705066515709916075139"/>
    <t1 m="i246,0.1754312685351500089581123,0.1754312685351500089581123,2008" d="0.1754312685351500089581123"/>
    <t1 m="i250,0.4786626900843199972079844,0.4786626900843199972079844,2008" d="0.4786626900843199972079844"/>
    <t1 m="i254,1.328851808196080064305988,1.328851808196080064305988,2008" d="1.328851808196080064305988"/>
    <t1 m="i256,2.816756011414499827338886,2.816756011414499827338886,2008" d="2.816756011414499827338886"/>
    <t1 m="i257,2.107515038549519825750167,2.107515038549519825750167,2008" d="2.107515038549519825750167"/>
  </data>
</indicator>
